abssctl/__init__.py
abssctl/__main__.py
abssctl/cli.py
abssctl/config.py
abssctl/locking.py
abssctl/logging.py
abssctl/providers/__init__.py
abssctl/providers/instance_status_provider.py
abssctl/providers/nginx.py
abssctl/providers/systemd.py
abssctl/providers/version_provider.py
abssctl/state/__init__.py
abssctl/state/registry.py
abssctl/templates/__init__.py
abssctl/templates/builtin/nginx/site.conf.j2
abssctl/templates/builtin/systemd/service.j2
abssctl-0.1.3a1.dist-info/METADATA
abssctl-0.1.3a1.dist-info/WHEEL
abssctl-0.1.3a1.dist-info/entry_points.txt
abssctl-0.1.3a1.dist-info/licenses/LICENSE
abssctl-0.1.3a1.dist-info/RECORD
