Metadata-Version: 2.3
Name: abssctl
Version: 0.1.3a1
Summary: Actual Budget Multi-Instance Sync Server Admin CLI
Project-URL: Homepage, https://doccyblade.github.io/abssctl/
Project-URL: Discussions, https://github.com/DocCyblade/abssctl/discussions
Project-URL: Issues, https://github.com/DocCyblade/abssctl/issues
Project-URL: Source, https://github.com/DocCyblade/abssctl
Project-URL: CI, https://github.com/DocCyblade/abssctl/actions
Project-URL: Changelog, https://github.com/DocCyblade/abssctl/blob/dev-alpha3/CHANGELOG.rst
Project-URL: Roadmap, https://github.com/DocCyblade/abssctl/blob/dev-alpha3/docs/roadmap.rst
Project-URL: License, https://github.com/DocCyblade/abssctl/blob/dev-alpha3/LICENSE
Author-email: Ken Robinson <doccyblade@homepost.org>
License: MIT License
Keywords: actual,admin,budget,cli,turnkey
Classifier: Development Status :: 2 - Pre-Alpha
Classifier: Intended Audience :: System Administrators
Classifier: License :: OSI Approved :: MIT License
Classifier: Operating System :: POSIX :: Linux
Classifier: Programming Language :: Python
Classifier: Programming Language :: Python :: 3
Classifier: Programming Language :: Python :: 3.11
Classifier: Programming Language :: Python :: 3.12
Classifier: Topic :: System :: Systems Administration
Classifier: Topic :: Utilities
Requires-Python: >=3.11
Requires-Dist: jinja2>=3.1
Requires-Dist: pyyaml>=6.0
Requires-Dist: rich>=13.7
Requires-Dist: typer>=0.12.3
Provides-Extra: dev
Requires-Dist: hatch>=1.14.2; extra == 'dev'
Requires-Dist: mypy>=1.11; extra == 'dev'
Requires-Dist: pytest-cov>=5.0; extra == 'dev'
Requires-Dist: pytest>=8.3; extra == 'dev'
Requires-Dist: pyyaml>=6.0.3; extra == 'dev'
Requires-Dist: ruff>=0.5.5; extra == 'dev'
Requires-Dist: sphinx-autobuild>=2024.4; extra == 'dev'
Requires-Dist: sphinx-rtd-theme; extra == 'dev'
Requires-Dist: sphinx>=7.4; extra == 'dev'
Requires-Dist: types-pyyaml>=6.0.12; extra == 'dev'
